jollyip/__init__.py
jollyip/cli.py
jollyip/commands.py
jollyip/formatting.py
jollyip/types.py
jollyip-0.0.3.dist-info/entry_points.txt
jollyip-0.0.3.dist-info/LICENSE
jollyip-0.0.3.dist-info/WHEEL
jollyip-0.0.3.dist-info/METADATA
jollyip-0.0.3.dist-info/RECORD
