Metadata-Version: 2.1
Name: jollyip
Version: 0.0.3
Summary: Scan an IP range, but happily
Home-page: https://github.com/checktheroads/jollyip
License: MIT
Keywords: networking,ping,icmp,command line,cli
Author: Matt Love
Author-email: matt@allroads.io
Requires-Python: >=3.6,<4.0
Classifier: License :: OSI Approved :: MIT License
Classifier: Programming Language :: Python :: 3
Classifier: Programming Language :: Python :: 3.6
Classifier: Programming Language :: Python :: 3.7
Classifier: Programming Language :: Python :: 3.8
Requires-Dist: click (>=7.0,<8.0)
Requires-Dist: icmplib (>=1.0.2,<2.0.0)
Requires-Dist: rich (>=0.3.3,<0.4.0)
Project-URL: Repository, https://github.com/checktheroads/jollyip
